app/__init__.py
app/main.py
app/models.py
app/py.typed
app/api/__init__.py
app/api/dependencies.py
app/api/main.py
app/api/routers/__init__.py
app/api/routers/account_types.py
app/api/routers/accounts.py
app/api/routers/projects.py
app/api/routers/system.py
app/api/routers/utils.py
app/core/__init__.py
app/core/database.py
app/static/404.html
app/static/favicon.ico
app/static/file.svg
app/static/globe.svg
app/static/index.html
app/static/index.txt
app/static/window.svg
app/static/_next/static/chunks/046eaacf-f97bb645ac7bf5fa.js
app/static/_next/static/chunks/11eacf67-4b90da578a5ca7e9.js
app/static/_next/static/chunks/135-c4b21292ddd65b5a.js
app/static/_next/static/chunks/300.ea121d794ae72b3e.js
app/static/_next/static/chunks/516-3f6e1ac5abd67dfd.js
app/static/_next/static/chunks/521.1a2b9606d70809e9.js
app/static/_next/static/chunks/954-e7634333dfe29a67.js
app/static/_next/static/chunks/framework-c5868d49362304ac.js
app/static/_next/static/chunks/main-app-5e70faeb44cd6ae9.js
app/static/_next/static/chunks/main-ce371ee36584fdae.js
app/static/_next/static/chunks/polyfills-42372ed130431b0a.js
app/static/_next/static/chunks/webpack-53307d3d75091628.js
app/static/_next/static/chunks/app/layout-dec168a4ccce5133.js
app/static/_next/static/chunks/app/loading-dd3bb05531589d55.js
app/static/_next/static/chunks/app/page-a03f8d95bed22256.js
app/static/_next/static/chunks/app/_not-found/page-f2f9b33be6d6cfa5.js
app/static/_next/static/chunks/pages/_app-3e433b9a76e171af.js
app/static/_next/static/chunks/pages/_error-84cf546debef433e.js
app/static/_next/static/css/37a9aa87c6d8917d.css
app/static/_next/static/media/26a46d62cd723877-s.woff2
app/static/_next/static/media/55c55f0601d81cf3-s.woff2
app/static/_next/static/media/581909926a08bbc8-s.woff2
app/static/_next/static/media/6d93bde91c0c2823-s.woff2
app/static/_next/static/media/97e0cb1ae144a2a9-s.woff2
app/static/_next/static/media/a34f9d1faa5f3315-s.p.woff2
app/static/_next/static/media/df0a9ae256c0569c-s.woff2
git_account_manager-0.1.6.dist-info/METADATA
git_account_manager-0.1.6.dist-info/WHEEL
git_account_manager-0.1.6.dist-info/entry_points.txt
git_account_manager-0.1.6.dist-info/RECORD
